json_np/__init__.py
json_np/json_np.py
json_np-0.0.6.dist-info/LICENSE
json_np-0.0.6.dist-info/METADATA
json_np-0.0.6.dist-info/WHEEL
json_np-0.0.6.dist-info/top_level.txt
json_np-0.0.6.dist-info/RECORD
