Metadata-Version: 2.1
Name: json-np
Version: 0.0.6
Summary: Json serialization extended to dates, numpy arrays, and more
Author-email: Luca de Alfaro <luca@dealfaro.com>, Massimo Di Pierro <massimo.dipierro@gmail.com>
License: MIT License
Project-URL: Homepage, https://github.com/lucadealfaro/json_np
Project-URL: Bug Tracker, https://github.com/lucadealfaro/json_np/issues
Classifier: Development Status :: 3 - Alpha
Classifier: Intended Audience :: Developers
Classifier: License :: OSI Approved :: MIT License
Classifier: Operating System :: OS Independent
Classifier: Programming Language :: Python :: 3
Classifier: Programming Language :: Python :: Implementation :: CPython
Classifier: Topic :: Software Development :: Libraries :: Python Modules
Requires-Python: >=3.7
License-File: LICENSE
Requires-Dist: numpy
